sapphire/__init__.py
sapphire/benchmark.py
sapphire/cuda.py
sapphire/lariat.py
sapphire/libsapphire.dylib
sapphire/libsapphire_gpu.dylib
sapphire/libsapphire_ultra.dylib
sapphire/libsapphire_vdsp.dylib
sapphire/llama.py
sapphire/loader.py
sapphire/native.py
sapphire/native_old.py
sapphire/nn.py
sapphire/ops.py
sapphire/shader_playground.py
sapphire/silicon_synthesis.py
sapphire/unified.py
sapphire_compute-1.0.1.dist-info/METADATA
sapphire_compute-1.0.1.dist-info/WHEEL
sapphire_compute-1.0.1.dist-info/top_level.txt
sapphire_compute-1.0.1.dist-info/RECORD
