Metadata-Version: 2.4
Name: sapphire-compute
Version: 1.0.1
Summary: SAPPHIRE: High-Performance Compute Acceleration Framework for Apple Silicon
Author-email: Svector Corporation <team@svector.co.in>
License: MIT
Project-URL: Homepage, https://github.com/svector-corporation/sapphire
Project-URL: Documentation, https://sapphire.svector.co.in
Project-URL: Repository, https://github.com/svector-corporation/sapphire
Project-URL: Issues, https://github.com/svector-corporation/sapphire/issues
Keywords: apple-silicon,amx,cuda,gpu-computing,machine-learning,deep-learning,neural-network,matrix-multiplication,blas,flash-attention,transformer,llm,inference,training
Classifier: Development Status :: 5 - Production/Stable
Classifier: Intended Audience :: Developers
Classifier: Intended Audience :: Science/Research
Classifier: License :: OSI Approved :: MIT License
Classifier: Operating System :: MacOS :: MacOS X
Classifier: Programming Language :: Python :: 3
Classifier: Programming Language :: Python :: 3.10
Classifier: Programming Language :: Python :: 3.11
Classifier: Programming Language :: Python :: 3.12
Classifier: Topic :: Scientific/Engineering :: Artificial Intelligence
Classifier: Topic :: Software Development :: Libraries :: Python Modules
Requires-Python: >=3.10
Requires-Dist: numpy>=1.24.0
Provides-Extra: dev
Requires-Dist: pytest>=7.0.0; extra == "dev"
Requires-Dist: pytest-benchmark>=4.0.0; extra == "dev"
Provides-Extra: full
Requires-Dist: torch>=2.0.0; extra == "full"
Requires-Dist: transformers>=4.30.0; extra == "full"
